{"XodlT1NPsCbeTM3OusHhvg==":"mbr-1646x1097.jpg","seu0yzeuTwtiz15mynudgA==":"mbr-121x109.png","XYJgDdrsGy3xCmS3WVDVeA==":"mbr-1076x717.jpg","/W+xDpg8hoku9+syuld7Bg==":"mbr-1-1076x717.jpg","twY8xtJIN5x6N9VInjeiwg==":"mbr-696x446.jpg","6iCedDf92IX5Y6o5hBdkXQ==":"mbr-696x522.jpg","UknTRiR+J02yJoA0rE9+ZQ==":"mbr-696x464.jpg","JAwhDjTdVetva87PGLOVDA==":"mbr-1920x1280.jpg","01u1ZFXYLm6awFMPImjEJw==":"mbr-1-1920x1280.jpg","QeK3BCiJq51mGKIAX4hVow==":"mbr-1920x1271.jpg","IBWxUH60IB1OMPoyZmJIvQ==":"mbr-1920x1330.png","pUNoKTaXKH35I0dMcwc3+Q==":"mbr-1618x1080.jpg","fdpOvaQN9+Xif9SL0crIRg==":"mbr-696x461.jpg","ERnBWfskEwHXOuk16JanhA==":"mbr-696x475.jpg","tUZRPsDwKfEMxlhbR6LFsA==":"mbr-696x435.jpg","eSjTf4QHITbqPOkffwkjnQ==":"mbr-696x492.jpg","25EyxdqHZXhU34hWA9xORA==":"mbr-1-696x464.jpg","oF819HT5pCzXiJXU+Khwkw==":"mbr-2-696x464.jpg","lqepMZW+09c7+fV/HuMyVg==":"mbr-696x471.png","EbaPYJwjYV3iwy+atshTAg==":"mbr-3-696x464.jpg","UfTDD3FR77yVQ3sAUQyzqw==":"mbr-1-696x461.jpg","xBmCt8KBFUezbETK4xKdcQ==":"mbr-1-696x492.jpg","75MTuF/Ixp6GMhHX8+tGNA==":"mbr-4-696x464.jpg","QwkeZ2kFY0EAxoMrvuEhkg==":"mbr-696x392.jpg","HrLb3X9IFAMPWiPs27Cvgw==":"mbr-1920x1080.jpg","zZkymocmum43JUYqq+YV6A==":"mbr-1920x1200.jpg","KwcpDw7Z8uLiJII32TJ0JQ==":"mbr-720x1080.jpg","PVOrXvwfPP46J+X4CnWdcA==":"mbr-1920x1440.jpg","cOWHRa16++1o30pZXmGO7g==":"mbr-578x385.jpg"}